pretix_passbook/__init__.py
pretix_passbook/apps.py
pretix_passbook/forms.py
pretix_passbook/passbook.py
pretix_passbook/signals.py
pretix_passbook/locale/django.pot
pretix_passbook/locale/djangojs.pot
pretix_passbook/locale/ar/LC_MESSAGES/django.mo
pretix_passbook/locale/ar/LC_MESSAGES/django.po
pretix_passbook/locale/ar/LC_MESSAGES/djangojs.mo
pretix_passbook/locale/ar/LC_MESSAGES/djangojs.po
pretix_passbook/locale/ca/LC_MESSAGES/django.mo
pretix_passbook/locale/ca/LC_MESSAGES/django.po
pretix_passbook/locale/ca/LC_MESSAGES/djangojs.mo
pretix_passbook/locale/ca/LC_MESSAGES/djangojs.po
pretix_passbook/locale/cs/LC_MESSAGES/django.mo
pretix_passbook/locale/cs/LC_MESSAGES/django.po
pretix_passbook/locale/cs/LC_MESSAGES/djangojs.mo
pretix_passbook/locale/cs/LC_MESSAGES/djangojs.po
pretix_passbook/locale/da/LC_MESSAGES/django.mo
pretix_passbook/locale/da/LC_MESSAGES/django.po
pretix_passbook/locale/da/LC_MESSAGES/djangojs.mo
pretix_passbook/locale/da/LC_MESSAGES/djangojs.po
pretix_passbook/locale/de/LC_MESSAGES/django.mo
pretix_passbook/locale/de/LC_MESSAGES/django.po
pretix_passbook/locale/de/LC_MESSAGES/djangojs.mo
pretix_passbook/locale/de/LC_MESSAGES/djangojs.po
pretix_passbook/locale/de_Informal/.gitkeep
pretix_passbook/locale/de_Informal/LC_MESSAGES/django.mo
pretix_passbook/locale/de_Informal/LC_MESSAGES/django.po
pretix_passbook/locale/de_Informal/LC_MESSAGES/djangojs.mo
pretix_passbook/locale/de_Informal/LC_MESSAGES/djangojs.po
pretix_passbook/locale/el/LC_MESSAGES/django.mo
pretix_passbook/locale/el/LC_MESSAGES/django.po
pretix_passbook/locale/el/LC_MESSAGES/djangojs.mo
pretix_passbook/locale/el/LC_MESSAGES/djangojs.po
pretix_passbook/locale/es/LC_MESSAGES/django.mo
pretix_passbook/locale/es/LC_MESSAGES/django.po
pretix_passbook/locale/es/LC_MESSAGES/djangojs.mo
pretix_passbook/locale/es/LC_MESSAGES/djangojs.po
pretix_passbook/locale/eu/LC_MESSAGES/djangojs.mo
pretix_passbook/locale/eu/LC_MESSAGES/djangojs.po
pretix_passbook/locale/fi/LC_MESSAGES/django.mo
pretix_passbook-1.13.3.dist-info/LICENSE
pretix_passbook-1.13.3.dist-info/METADATA
pretix_passbook-1.13.3.dist-info/WHEEL
pretix_passbook-1.13.3.dist-info/entry_points.txt
pretix_passbook-1.13.3.dist-info/top_level.txt
pretix_passbook-1.13.3.dist-info/RECORD
