Metadata-Version: 2.2
Name: pretix-passbook
Version: 1.13.3
Summary: Passbook tickets for pretix
Author-email: pretix team <support@pretix.eu>, Tobias Kunze <rixx@cutebit.de>
Maintainer-email: pretix team <support@pretix.eu>
License: Copyright 2016 Tobias 'rixx' Kunze and Raphael Michel
Project-URL: homepage, https://github.com/pretix/pretix-passbook
Keywords: pretix
Requires-Python: >=3.9
License-File: LICENSE
Requires-Dist: wallet-py3k
Requires-Dist: googlemaps
